{
	"configurations" : 
	[
		{
			"directories" : 
			[
				{
					"build" : ".",
					"hasInstallRule" : true,
					"jsonFile" : "directory-.-d457512b397a912647a6.json",
					"minimumCMakeVersion" : 
					{
						"string" : "3.12"
					},
					"projectIndex" : 0,
					"source" : ".",
					"targetIndexes" : 
					[
						0,
						1
					]
				}
			],
			"name" : "",
			"projects" : 
			[
				{
					"directoryIndexes" : 
					[
						0
					],
					"name" : "yahboomcar_laser",
					"targetIndexes" : 
					[
						0,
						1
					]
				}
			],
			"targets" : 
			[
				{
					"directoryIndex" : 0,
					"id" : "uninstall::@6890427a1f51a3e7e1df",
					"jsonFile" : "target-uninstall-a04a246513a626a9b065.json",
					"name" : "uninstall",
					"projectIndex" : 0
				},
				{
					"directoryIndex" : 0,
					"id" : "yahboomcar_laser_uninstall::@6890427a1f51a3e7e1df",
					"jsonFile" : "target-yahboomcar_laser_uninstall-9ebb6ff6d35be4e88e2e.json",
					"name" : "yahboomcar_laser_uninstall",
					"projectIndex" : 0
				}
			]
		}
	],
	"kind" : "codemodel",
	"paths" : 
	{
		"build" : "/home/jetson/yahboomcar_ws/src/yahboomcar_laser/build/yahboomcar_laser",
		"source" : "/home/jetson/yahboomcar_ws/src/yahboomcar_laser"
	},
	"version" : 
	{
		"major" : 2,
		"minor" : 3
	}
}
